snowland_py253/__init__.py
snowland_py253/account.py
snowland_py253/account_manage.py
snowland_py253/common.py
snowland_py253/internal_message.py
snowland_py253-0.0.2.dist-info/DESCRIPTION.rst
snowland_py253-0.0.2.dist-info/METADATA
snowland_py253-0.0.2.dist-info/RECORD
snowland_py253-0.0.2.dist-info/WHEEL
snowland_py253-0.0.2.dist-info/metadata.json
snowland_py253-0.0.2.dist-info/top_level.txt
