Metadata-Version: 2.0
Name: snowland-py253
Version: 0.0.2
Summary: Python3 SDK for 253.com (SMS)
Home-page: https://gitee.com/snowlandltd/snowland-253-python
Author: A.Star
Author-email: astar@snowland.ltd
License: Apache v2.0 License
Platform: all
Classifier: Operating System :: OS Independent
Classifier: Intended Audience :: Developers
Classifier: License :: OSI Approved :: Apache Software License
Classifier: Programming Language :: Python
Classifier: Programming Language :: Python :: Implementation
Classifier: Programming Language :: Python :: 3
Classifier: Programming Language :: Python :: 3.6
Classifier: Programming Language :: Python :: 3.7
Classifier: Programming Language :: Python :: 3.8
Classifier: Topic :: Software Development :: Libraries
Requires-Dist: snowland-authsdk (>=0.0.4)
Requires-Dist: astartool (>=0.0.5)
Requires-Dist: configparser
Requires-Dist: requests
